pydantic_odm/__init__.py
pydantic_odm/db.py
pydantic_odm/errors.py
pydantic_odm/mixins.py
pydantic_odm/types.py
pydantic_odm/decoders/__init__.py
pydantic_odm/decoders/mongodb.py
pydantic_odm/encoders/__init__.py
pydantic_odm/encoders/mongodb.py
pydantic_odm-0.2.5.dist-info/LICENSE
pydantic_odm-0.2.5.dist-info/METADATA
pydantic_odm-0.2.5.dist-info/WHEEL
pydantic_odm-0.2.5.dist-info/top_level.txt
pydantic_odm-0.2.5.dist-info/RECORD
